mutamr/CustomLog.py
mutamr/Fastq2vcf.py
mutamr/Utils.py
mutamr/__init__.py
mutamr/mutamr.py
mutamr/references/Mtb_NC000962.3.fa
mutamr/references/Mtb_NC000962.3.fa.amb
mutamr/references/Mtb_NC000962.3.fa.ann
mutamr/references/Mtb_NC000962.3.fa.bwt
mutamr/references/Mtb_NC000962.3.fa.fai
mutamr/references/Mtb_NC000962.3.fa.pac
mutamr/references/Mtb_NC000962.3.fa.sa
mutamr/references/NC_000962.3.fa
mutamr/references/NC_000962.3.gbk
mutamr/references/snpEff.config
mutamr/references/Mycobacterium_tuberculosis_h37rv/snpEffectPredictor.bin
mutamr-0.0.2.dist-info/licenses/LICENSE
mutamr-0.0.2.dist-info/METADATA
mutamr-0.0.2.dist-info/WHEEL
mutamr-0.0.2.dist-info/entry_points.txt
mutamr-0.0.2.dist-info/top_level.txt
mutamr-0.0.2.dist-info/RECORD
