Metadata-Version: 2.4
Name: mutamr
Version: 0.0.2
Summary: Variant detection for AMR prediction
Home-page: https://github.com/MDU-PHL/mutamr
Author: Kristy Horan
Author-email: kristyhoran15@gmail.com
Maintainer: Kristy Horan
Maintainer-email: kristyhoran15@gmail.com
Classifier: Development Status :: 4 - Beta
Classifier: Programming Language :: Python :: Implementation :: CPython
Classifier: Intended Audience :: Science/Research
Classifier: License :: OSI Approved :: GNU General Public License v3 (GPLv3)
Classifier: Natural Language :: English
Classifier: Programming Language :: Python :: 3 :: Only
Classifier: Programming Language :: Python :: 3.6
Classifier: Programming Language :: Python :: 3.7
Classifier: Topic :: Scientific/Engineering :: Bio-Informatics
Requires-Python: >=3.10, <4
License-File: LICENSE
Requires-Dist: pytest
Dynamic: author
Dynamic: author-email
Dynamic: classifier
Dynamic: description
Dynamic: description-content-type
Dynamic: home-page
Dynamic: license-file
Dynamic: maintainer
Dynamic: maintainer-email
Dynamic: requires-dist
Dynamic: requires-python
Dynamic: summary
